codecrate/__init__.py
codecrate/_version.py
codecrate/cli.py
codecrate/config.py
codecrate/diffgen.py
codecrate/discover.py
codecrate/ids.py
codecrate/manifest.py
codecrate/markdown.py
codecrate/mdparse.py
codecrate/model.py
codecrate/packer.py
codecrate/parse.py
codecrate/stubber.py
codecrate/token_budget.py
codecrate/udiff.py
codecrate/unpacker.py
codecrate/validate.py
codecrate-0.1.1.dist-info/licenses/LICENSE
codecrate-0.1.1.dist-info/METADATA
codecrate-0.1.1.dist-info/WHEEL
codecrate-0.1.1.dist-info/entry_points.txt
codecrate-0.1.1.dist-info/top_level.txt
codecrate-0.1.1.dist-info/RECORD
